CustomLogging.py
DecoratorLogging.py
DemoLogging.py
GenericListenerLogging.py
Handler.py
LICENSE.txt
LibraryListenerLogging.py
MANIFEST.in
PropertyLogging.py
README.rst
RobotLog.py
setup.cfg
setup.py
loggingExamples.egg-info/PKG-INFO
loggingExamples.egg-info/SOURCES.txt
loggingExamples.egg-info/dependency_links.txt
loggingExamples.egg-info/requires.txt
loggingExamples.egg-info/top_level.txt