Metadata-Version: 1.1
Name: loggingExamples
Version: 1.0.0
Summary: A Python project to demo Logging
Home-page: https://github.com/pypa/sampleproject
Author: Shiva Kumar Gone
Author-email: shiva.k.g@gmail.com
License: MIT
Keywords: demo logging
Platform: UNKNOWN
Classifier: Development Status :: 3 - Alpha
Classifier: Intended Audience :: Developers
Classifier: Topic :: Software Development :: Build Tools
Classifier: License :: OSI Approved :: MIT License
Classifier: Programming Language :: Python :: 2
Classifier: Programming Language :: Python :: 2.7
Classifier: Programming Language :: Python :: 3
Classifier: Programming Language :: Python :: 3.3
Classifier: Programming Language :: Python :: 3.4
Classifier: Programming Language :: Python :: 3.5
